bew-wz/__init__.py
bew-wz/test.py
bew_wz/__init__.py
bew_wz/test.py
leo_wei_test1-0.0.3.dist-info/LICENSE
leo_wei_test1-0.0.3.dist-info/METADATA
leo_wei_test1-0.0.3.dist-info/WHEEL
leo_wei_test1-0.0.3.dist-info/top_level.txt
leo_wei_test1-0.0.3.dist-info/RECORD
