Metadata-Version: 2.1
Name: leo-wei-test1
Version: 0.0.3
Summary: PyPI Tutorial
Home-page: https://github.com/
Author: leowei
Author-email: 89430245@qq.com
License: UNKNOWN
Platform: UNKNOWN
Classifier: Programming Language :: Python :: 3
Classifier: License :: OSI Approved :: MIT License
Classifier: Operating System :: OS Independent
License-File: LICENSE
